aws_syndicate-1.19.0.dist-info/licenses/LICENSE
syndicate/__init__.py
syndicate/exceptions.py
syndicate/commons/__init__.py
syndicate/commons/log_helper.py
syndicate/connection/__init__.py
syndicate/connection/api_gateway_connection.py
syndicate/connection/application_autoscaling_connection.py
syndicate/connection/appsync_connection.py
syndicate/connection/batch_connection.py
syndicate/connection/cloud_watch_connection.py
syndicate/connection/cloudfront_connection.py
syndicate/connection/cognito_identity_connection.py
syndicate/connection/cognito_identity_provider_connection.py
syndicate/connection/dax_connection.py
syndicate/connection/documentdb_connection.py
syndicate/connection/dynamo_connection.py
syndicate/connection/ec2_connection.py
syndicate/connection/elastic_beanstalk_connection.py
syndicate/connection/eventbridge_scheduler_connection.py
syndicate/connection/firehose_connection.py
syndicate/connection/helper.py
syndicate/connection/iam_connection.py
syndicate/connection/kinesis_connection.py
syndicate/connection/kms_connection.py
syndicate/connection/lambda_connection.py
syndicate/connection/rds_connection.py
syndicate/connection/resource_groups_tagging_api_connection.py
syndicate/connection/s3_connection.py
syndicate/connection/ses_connection.py
syndicate/connection/sns_connection.py
syndicate/connection/sqs_connection.py
syndicate/connection/step_functions_connection.py
syndicate/connection/sts_connection.py
syndicate/core/__init__.py
syndicate/core/constants.py
syndicate/core/decorators.py
syndicate/core/handlers.py
syndicate/core/helper.py
syndicate/core/build/__init__.py
syndicate/core/build/artifact_processor.py
syndicate/core/build/bundle_processor.py
syndicate/core/build/deployment_processor.py
syndicate/core/build/helper.py
syndicate/core/build/meta_processor.py
syndicate/core/build/profiler_processor.py
syndicate/core/build/warmup_processor.py
syndicate/core/build/runtime/__init__.py
syndicate/core/build/runtime/appsync.py
syndicate/core/build/runtime/dotnet.py
aws_syndicate-1.19.0.dist-info/METADATA
aws_syndicate-1.19.0.dist-info/WHEEL
aws_syndicate-1.19.0.dist-info/entry_points.txt
aws_syndicate-1.19.0.dist-info/top_level.txt
aws_syndicate-1.19.0.dist-info/zip-safe
aws_syndicate-1.19.0.dist-info/RECORD
