Metadata-Version: 2.4
Name: aws-syndicate
Version: 1.19.0
Summary: AWS-syndicate is an Amazon Web Services deployment framework written in Python, which allows to easily deploy serverless applications using resource descriptions.
Author-email: EPAM Systems <support@syndicate.team>
Project-URL: Homepage, https://github.com/epam/aws-syndicate
Project-URL: Documentation, https://github.com/epam/aws-syndicate/wiki
Project-URL: Changelog, https://github.com/epam/aws-syndicate/blob/master/CHANGELOG.md
Keywords: AWS,SERVERLESS,CLOUD,LAMBDA,DEPLOY
Platform: Linux
Platform: Windows
Classifier: Development Status :: 5 - Production/Stable
Classifier: Intended Audience :: Developers
Classifier: Topic :: Software Development :: Build Tools
Classifier: Programming Language :: Python :: 3.10
Requires-Python: >=3.10
License-File: LICENSE
Requires-Dist: click==7.1.2
Requires-Dist: botocore==1.38.12
Requires-Dist: boto3==1.38.12
Requires-Dist: tqdm==4.67.1
Requires-Dist: pyyaml==6.0.1
Requires-Dist: requests-aws-sign==0.1.6
Requires-Dist: requests==2.32.3
Requires-Dist: tabulate==0.9.0
Requires-Dist: troposphere==4.1.0
Dynamic: license-file
